faster-whisper-api-proxy/__init__.py
faster-whisper-api-proxy/proxy.py
faster-whisper-api-proxy/version.py
faster_whisper_api_proxy/__init__.py
faster_whisper_api_proxy/proxy.py
faster_whisper_api_proxy/version.py
src/faster-whisper-api-proxy/proxy.py
src/faster-whisper-api-proxy/version.py
faster_whisper_api_proxy-0.0.1.dist-info/METADATA
faster_whisper_api_proxy-0.0.1.dist-info/WHEEL
faster_whisper_api_proxy-0.0.1.dist-info/top_level.txt
faster_whisper_api_proxy-0.0.1.dist-info/RECORD
